g2g/__init__.py
g2g/gitlab_utils.py
g2g/main.py
g2g-0.1.5.dist-info/LICENSE
g2g-0.1.5.dist-info/METADATA
g2g-0.1.5.dist-info/WHEEL
g2g-0.1.5.dist-info/entry_points.txt
g2g-0.1.5.dist-info/RECORD
